blackbox_schemas/__init__.py
blackbox_schemas/models.py
blackbox_schemas-2.0.20.dist-info/METADATA
blackbox_schemas-2.0.20.dist-info/WHEEL
blackbox_schemas-2.0.20.dist-info/top_level.txt
blackbox_schemas-2.0.20.dist-info/RECORD
