Metadata-Version: 2.4
Name: blackbox-schemas
Version: 2.0.20
Summary: Consolidated Pydantic v2 schemas for BlackBox LLM operations
Home-page: https://github.com/isandeepmakwana1/blackbox-schemas
Author: BlackBox AI
Author-email: BlackBox AI <your.email@example.com>
License-Expression: MIT
Project-URL: Homepage, https://github.com/isandeepmakwana1/blackbox-schemas
Project-URL: Repository, https://github.com/isandeepmakwana1/blackbox-schemas
Project-URL: Documentation, https://github.com/isandeepmakwana1/blackbox-schemas#readme
Keywords: pydantic,schemas,llm,blackbox,ai
Classifier: Development Status :: 4 - Beta
Classifier: Intended Audience :: Developers
Classifier: Programming Language :: Python :: 3
Classifier: Programming Language :: Python :: 3.8
Classifier: Programming Language :: Python :: 3.9
Classifier: Programming Language :: Python :: 3.10
Classifier: Programming Language :: Python :: 3.11
Classifier: Programming Language :: Python :: 3.12
Classifier: Topic :: Software Development :: Libraries :: Python Modules
Requires-Python: >=3.8
Requires-Dist: pydantic<3.0.0,>=2.0.0
Requires-Dist: typing-extensions>=4.0.0
Dynamic: author
Dynamic: home-page
Dynamic: requires-python
